[
  {
    "id": "1",
    "firstName": "Adinnu",
    "lastName": "Gift",
    "email": "giftad124@gmail.com",
    "gender": "Male",
    "speciality": "Adult care",
    "availabilities": [
      {
        "day": "Mon, Sep 30",
        "shifts": ["7:00 AM - 3:00 PM", "11:00 PM - 7:00 PM"]
      },
      {
        "day": "Tue, Oct 01",
        "shifts": [
          "7:00 AM - 3:00 PM",
          "3:00 PM - 11:00 PM",
          "11:00 PM - 7:00 PM"
        ]
      },
      {
        "day": "Wed, Oct 02",
        "shifts": ["11:00 PM - 7:00 PM"]
      },
      {
        "day": "Thu, Oct 03",
        "shifts": ["7:00 AM - 3:00 PM", "3:00 PM - 11:00 PM"]
      },
      {
        "day": "Fri, Oct 04",
        "shifts": ["3:00 PM - 11:00 PM"]
      }
    ],
    "languages": ["English", "Hausa", "Yoruba"],
    "about": "Lorem ipsum dolor sit amet, consectetur adipiscing elit, sed do eiusmod tempor incididunt ut labore et dolore magna aliqua. Ut enim ad minim veniam, quis nostrud exercitation ullamco laboris nisi ut aliquip ex ea commodo consequat. Duis aute irure   dolor in reprehenderit in voluptate velit esse cillum dolore eu fugiat nulla pariatur. Excepteur sint occaecat cupidatat non proident, sunt in culpa qui officia deserunt mollit anim id est laborum.",
    "address": "5 Morenike Cl, Allen",
    "city": "Ikeja",
    "state": "Lagos",
    "postalCode": 100212,
    "location": {
      "longitude": 3.30413,
      "latitude": 6.63585
    },
    "reviews": [
      {
        "reviewId": 1,
        "rating": 5,
        "liked": true,
        "comment": "Competent, professional, creates high confidence in medical judgement",
        "verifiedPatient": true,
        "createdAt": "1 week ago"
      },
      {
        "reviewId": 2,
        "rating": 2,
        "liked": false,
        "comment": "Incompetent, unprofessional, creates high confidence in medical judgement",
        "verifiedPatient": true,
        "createdAt": "2 week ago"
      },
      {
        "reviewId": 3,
        "rating": 4,
        "liked": true,
        "comment": "Competent, professional, creates high confidence in medical judgement",
        "verifiedPatient": false,
        "createdAt": "2 week ago"
      }
    ]
  },
  {
    "id": " 2",
    "firstName": "Chinecherem",
    "lastName": "Ezeokoli",
    "email": "chiokoli45678@gmail.com",
    "gender": "Female",
    "speciality": "Children care",
    "availabilities": [
      {
        "day": "Mon, Sep 30",
        "shifts": ["7:00 AM - 3:00 PM", "11:00 PM - 7:00 PM"]
      },
      {
        "day": "Tue, Oct 01",
        "shifts": [
          "7:00 AM - 3:00 PM",
          "3:00 PM - 11:00 PM",
          "11:00 PM - 7:00 PM"
        ]
      },
      {
        "day": "Wed, Oct 02",
        "shifts": ["11:00 PM - 7:00 PM"]
      },
      {
        "day": "Thu, Oct 03",
        "shifts": ["7:00 AM - 3:00 PM", "3:00 PM - 11:00 PM"]
      },
      {
        "day": "Fri, Oct 04",
        "shifts": ["3:00 PM - 11:00 PM"]
      }
    ],
    "languages": ["English", "Ibo"],
    "about": "Lorem ipsum dolor sit amet, consectetur adipiscing elit, sed do eiusmod tempor incididunt ut labore et dolore magna aliqua. ",
    "address": "10 Amore Street",
    "city": "Ikeja",
    "state": "Lagos",
    "postalCode": 101233,
    "location": {
      "longitude": 3.34988,
      "latitude": 6.59807
    },
    "reviews": [
      {
        "reviewId": 1,
        "rating": 5,
        "liked": true,
        "comment": "Competent, professional, creates high confidence in medical judgement",
        "verifiedPatient": true,
        "createdAt": "1 week ago"
      },
      {
        "reviewId": 2,
        "rating": 2,
        "liked": false,
        "comment": "Incompetent, unprofessional, creates high confidence in medical judgement",
        "verifiedPatient": true,
        "createdAt": "2 week ago"
      },
      {
        "reviewId": 3,
        "rating": 4,
        "liked": true,
        "comment": "Competent, professional, creates high confidence in medical judgement",
        "verifiedPatient": false,
        "createdAt": "2 week ago"
      }
    ]
  },
  {
    "id": "3",
    "firstName": "Moses",
    "lastName": "Abolade",
    "email": "mobolad78@yahoo.com",
    "gender": "Male",
    "speciality": "Children care",
    "availabilities": [
      {
        "day": "Mon, Sep 30",
        "shifts": ["7:00 AM - 3:00 PM", "11:00 PM - 7:00 PM"]
      },
      {
        "day": "Tue, Oct 01",
        "shifts": [
          "7:00 AM - 3:00 PM",
          "3:00 PM - 11:00 PM",
          "11:00 PM - 7:00 PM"
        ]
      },
      {
        "day": "Wed, Oct 02",
        "shifts": ["11:00 PM - 7:00 PM"]
      },
      {
        "day": "Thu, Oct 03",
        "shifts": ["7:00 AM - 3:00 PM", "3:00 PM - 11:00 PM"]
      },
      {
        "day": "Fri, Oct 04",
        "shifts": ["3:00 PM - 11:00 PM"]
      }
    ],
    "languages": ["English", "Yoruba"],
    "about": "Lorem ipsum dolor sit amet, consectetur adipiscing elit, sed do eiusmod tempor incididunt ut labore et dolore magna aliqua. ",
    "address": "3 Bisi Ogabi Street",
    "city": "Ikeja",
    "state": "Lagos",
    "postalCode": 101233,
    "location": {
      "longitude": 3.34726,
      "latitude": 6.60067
    },
    "reviews": [
      {
        "reviewId": 1,
        "rating": 5,
        "liked": true,
        "comment": "Competent, professional, creates high confidence in medical judgement",
        "verifiedPatient": true,
        "createdAt": "1 week ago"
      },
      {
        "reviewId": 2,
        "rating": 2,
        "liked": false,
        "comment": "Incompetent, unprofessional, creates high confidence in medical judgement",
        "verifiedPatient": true,
        "createdAt": "2 week ago"
      },
      {
        "reviewId": 3,
        "rating": 4,
        "liked": true,
        "comment": "Competent, professional, creates high confidence in medical judgement",
        "verifiedPatient": false,
        "createdAt": "2 week ago"
      }
    ]
  },
  {
    "id": "4",
    "firstName": "Esther",
    "lastName": "Agbons",
    "email": "agbonser78@yahoo.com",
    "gender": "Female",
    "speciality": "Adult care",
    "availabilities": [
      {
        "day": "Mon, Sep 30",
        "shifts": ["7:00 AM - 3:00 PM", "11:00 PM - 7:00 PM"]
      },
      {
        "day": "Tue, Oct 01",
        "shifts": [
          "7:00 AM - 3:00 PM",
          "3:00 PM - 11:00 PM",
          "11:00 PM - 7:00 PM"
        ]
      },
      {
        "day": "Wed, Oct 02",
        "shifts": ["11:00 PM - 7:00 PM"]
      },
      {
        "day": "Thu, Oct 03",
        "shifts": ["7:00 AM - 3:00 PM", "3:00 PM - 11:00 PM"]
      },
      {
        "day": "Fri, Oct 04",
        "shifts": ["3:00 PM - 11:00 PM"]
      }
    ],
    "languages": ["English", "Isoko"],
    "about": "Lorem ipsum dolor sit amet, consectetur adipiscing elit, sed do eiusmod tempor incididunt ut labore et dolore magna aliqua. ",
    "address": "11 Adekunbi Crescent, Allen",
    "city": "Ikeja",
    "state": "Lagos",
    "postalCode": 101233,
    "location": {
      "longitude": 3.34767,
      "latitude": 6.60003
    },
    "reviews": [
      {
        "reviewId": 1,
        "rating": 5,
        "liked": true,
        "comment": "Competent, professional, creates high confidence in medical judgement",
        "verifiedPatient": true,
        "createdAt": "1 week ago"
      },
      {
        "reviewId": 2,
        "rating": 2,
        "liked": false,
        "comment": "Incompetent, unprofessional, creates high confidence in medical judgement",
        "verifiedPatient": true,
        "createdAt": "2 week ago"
      },
      {
        "reviewId": 3,
        "rating": 4,
        "liked": true,
        "comment": "Competent, professional, creates high confidence in medical judgement",
        "verifiedPatient": false,
        "createdAt": "2 week ago"
      }
    ]
  },
  {
    "id": "5",
    "firstName": "Kingsley",
    "lastName": "Amama",
    "email": "agbonser78@yahoo.com",
    "gender": "Male",
    "speciality": "Adult care",
    "availabilities": [
      {
        "day": "Mon, Sep 30",
        "shifts": ["7:00 AM - 3:00 PM", "11:00 PM - 7:00 PM"]
      },
      {
        "day": "Tue, Oct 01",
        "shifts": [
          "7:00 AM - 3:00 PM",
          "3:00 PM - 11:00 PM",
          "11:00 PM - 7:00 PM"
        ]
      },
      {
        "day": "Wed, Oct 02",
        "shifts": ["11:00 PM - 7:00 PM"]
      },
      {
        "day": "Thu, Oct 03",
        "shifts": ["7:00 AM - 3:00 PM", "3:00 PM - 11:00 PM"]
      },
      {
        "day": "Fri, Oct 04",
        "shifts": ["3:00 PM - 11:00 PM"]
      }
    ],
    "languages": ["English", "Ibibio"],
    "about": "Lorem ipsum dolor sit amet, consectetur adipiscing elit, sed do eiusmod tempor incididunt ut labore et dolore magna aliqua. ",
    "address": "2 Rev.Ogunbiyi St, Ikeja GRA",
    "city": "Ikeja",
    "state": "Lagos",
    "postalCode": 101233,
    "location": {
      "longitude": 3.33929,
      "latitude": 6.58973
    },
    "reviews": [
      {
        "reviewId": 1,
        "rating": 5,
        "liked": true,
        "comment": "Competent, professional, creates high confidence in medical judgement",
        "verifiedPatient": true,
        "createdAt": "1 week ago"
      },
      {
        "reviewId": 2,
        "rating": 2,
        "liked": false,
        "comment": "Incompetent, unprofessional, creates high confidence in medical judgement",
        "verifiedPatient": true,
        "createdAt": "2 week ago"
      },
      {
        "reviewId": 3,
        "rating": 4,
        "liked": true,
        "comment": "Competent, professional, creates high confidence in medical judgement",
        "verifiedPatient": false,
        "createdAt": "2 week ago"
      }
    ]
  }
]
